LICENSE.txt
MANIFEST.in
README.md
setup.py
rad2f5/__init__.py
rad2f5/rad2f5.py
rad2f5.egg-info/PKG-INFO
rad2f5.egg-info/SOURCES.txt
rad2f5.egg-info/dependency_links.txt
rad2f5.egg-info/requires.txt
rad2f5.egg-info/top_level.txt