Metadata-Version: 1.0
Name: rad2f5
Version: 3.4
Summary: A Python script to convert RadWare configuration to F5 syntax
Home-page: https://pypi.python.org/pypi?:action=display&name=rad2f5&version=3.4
Author: Pete White
Author-email: pwhite@f5.com
License: PSF
Platform: UNKNOWN
